{
  "results": [
    {
      "command": "cargo build --jobs 16 --release --example breakout",
      "mean": 75.46961307806001,
      "stddev": 0.23604443791143218,
      "median": 75.49435700286,
      "user": 1138.4420693,
      "system": 30.625021100000005,
      "min": 75.17783771986,
      "max": 75.78514042486,
      "times": [
        75.45693462586,
        75.78514042486,
        75.53177937986,
        75.58697003686,
        75.23390142686,
        75.76032000885999,
        75.69190378286,
        75.23910444486,
        75.17783771986,
        75.23223892986
      ],
      "exit_codes": [
        0,
        0,
        0,
        0,
        0,
        0,
        0,
        0,
        0,
        0
      ]
    }
  ]
}
