{
  "results": [
    {
      "command": "cargo build --jobs 16 --release --example breakout",
      "mean": 79.7872118722,
      "stddev": 0.27106388815294774,
      "median": 79.84150609099999,
      "user": 1203.5718345999999,
      "system": 30.819920859999996,
      "min": 79.348908915,
      "max": 80.092249674,
      "times": [
        80.092249674,
        79.724518699,
        80.056706995,
        79.387888416,
        79.585041134,
        79.998205591,
        79.348908915,
        79.789551596,
        79.89346058599999,
        79.995587116
      ],
      "exit_codes": [
        0,
        0,
        0,
        0,
        0,
        0,
        0,
        0,
        0,
        0
      ]
    }
  ]
}
