{
  "results": [
    {
      "command": "cargo build --jobs 16 --release --example breakout",
      "mean": 73.11195345198,
      "stddev": 0.3136263939140172,
      "median": 73.08895608628,
      "user": 1073.9488686999998,
      "system": 28.22593648,
      "min": 72.70239300878,
      "max": 73.59291878878,
      "times": [
        73.37313706078,
        73.37531161878,
        72.79058748378,
        72.81540749078,
        73.24265934278,
        73.37699600278,
        72.70239300878,
        72.93525282978,
        73.59291878878,
        72.91487089278
      ],
      "exit_codes": [
        0,
        0,
        0,
        0,
        0,
        0,
        0,
        0,
        0,
        0
      ]
    }
  ]
}
