{
  "results": [
    {
      "command": "cargo build --jobs 16 --release --example breakout",
      "mean": 97.19796958708001,
      "stddev": 0.8009918469254084,
      "median": 97.42570285308,
      "user": 1374.488294,
      "system": 33.8452642,
      "min": 95.63803347658,
      "max": 98.10096628858001,
      "times": [
        97.47069032058,
        97.65191043758,
        97.82305818258001,
        98.10096628858001,
        96.96368992158001,
        95.97929831958001,
        97.72580330058001,
        95.63803347658,
        97.38071538558,
        97.24553023758001
      ],
      "exit_codes": [
        0,
        0,
        0,
        0,
        0,
        0,
        0,
        0,
        0,
        0
      ]
    }
  ]
}
