{
  "results": [
    {
      "command": "cargo build --jobs 8 --release --example breakout",
      "mean": 120.32555670456001,
      "stddev": 0.3290077878133161,
      "median": 120.37003732246,
      "user": 922.1608887399998,
      "system": 24.2095123,
      "min": 119.69094741446,
      "max": 120.79267905246,
      "times": [
        120.49793672046,
        120.71835143546001,
        119.69094741446,
        120.79267905246,
        120.09310567046,
        120.32256064646,
        120.02041715746,
        120.42968509846,
        120.27236985146,
        120.41751399846001
      ],
      "exit_codes": [
        0,
        0,
        0,
        0,
        0,
        0,
        0,
        0,
        0,
        0
      ]
    }
  ]
}
