{
  "results": [
    {
      "command": "cargo build --jobs 16 --release --example breakout",
      "mean": 90.98683156391999,
      "stddev": 1.109063964663877,
      "median": 91.40633410461999,
      "user": 1263.0488972599999,
      "system": 30.876631979999996,
      "min": 89.31644835862,
      "max": 92.10895264662,
      "times": [
        89.31644835862,
        91.97046405662,
        90.96450242462,
        89.64674992862,
        91.48751162362,
        89.40630675862,
        91.79135924562,
        91.32515658562,
        92.10895264662,
        91.85086401062
      ],
      "exit_codes": [
        0,
        0,
        0,
        0,
        0,
        0,
        0,
        0,
        0,
        0
      ]
    }
  ]
}
