{
  "results": [
    {
      "command": "cargo build --jobs 8 --release --example breakout",
      "mean": 130.45367985644,
      "stddev": 0.11850534300712516,
      "median": 130.43908954864,
      "user": 999.19301866,
      "system": 24.298204539999993,
      "min": 130.28780923064,
      "max": 130.62854937564,
      "times": [
        130.31164736664,
        130.35122345664,
        130.60815973164,
        130.42684622164,
        130.28780923064,
        130.55739272864,
        130.42329018264,
        130.49054739464,
        130.45133287564,
        130.62854937564
      ],
      "exit_codes": [
        0,
        0,
        0,
        0,
        0,
        0,
        0,
        0,
        0,
        0
      ]
    }
  ]
}
