{
  "results": [
    {
      "command": "cargo build --jobs 16 --release --example breakout",
      "mean": 76.05111179494,
      "stddev": 0.34013098189701585,
      "median": 76.07932084644,
      "user": 1145.0132519200001,
      "system": 29.226105739999998,
      "min": 75.27283060644001,
      "max": 76.49258059644,
      "times": [
        75.92196444944,
        76.25459977744,
        76.09032585344,
        75.92665239644,
        76.37416189844001,
        75.27283060644001,
        76.22917911444,
        76.06831583944,
        76.49258059644,
        75.88050741744
      ],
      "exit_codes": [
        0,
        0,
        0,
        0,
        0,
        0,
        0,
        0,
        0,
        0
      ]
    }
  ]
}
