{
  "results": [
    {
      "command": "cargo build --jobs 16 --release --example breakout",
      "mean": 92.2068042063,
      "stddev": 1.0266898755491465,
      "median": 92.17843820270001,
      "user": 1286.95889932,
      "system": 31.495632060000002,
      "min": 91.0646371847,
      "max": 94.7142077437,
      "times": [
        91.0646371847,
        94.7142077437,
        92.6430682477,
        92.1129386897,
        91.6009771227,
        92.4088438647,
        91.5912556857,
        92.41190048870001,
        91.2762753197,
        92.24393771570001
      ],
      "exit_codes": [
        0,
        0,
        0,
        0,
        0,
        0,
        0,
        0,
        0,
        0
      ]
    }
  ]
}
