{
  "results": [
    {
      "command": "cargo build --jobs 8 --release --example breakout",
      "mean": 121.71080913104,
      "stddev": 0.2030174363819557,
      "median": 121.66133197104,
      "user": 933.2029898199999,
      "system": 24.6816285,
      "min": 121.44333525904,
      "max": 122.02791770204,
      "times": [
        121.49164859004,
        121.60633003504,
        121.56090186304,
        121.44333525904,
        121.67143731804,
        122.02791770204,
        121.95231278704,
        121.76658349604,
        121.93639763604,
        121.65122662404
      ],
      "exit_codes": [
        0,
        0,
        0,
        0,
        0,
        0,
        0,
        0,
        0,
        0
      ]
    }
  ]
}
