{
  "results": [
    {
      "command": "cargo build --jobs 8 --release --example breakout",
      "mean": 117.22944712792,
      "stddev": 0.29048883890870536,
      "median": 117.21334701232,
      "user": 902.88733982,
      "system": 24.832671819999998,
      "min": 116.85851695582,
      "max": 117.92836168682,
      "times": [
        117.31815528781999,
        117.08689022982,
        117.21202195782,
        117.36299613781999,
        117.23718519881999,
        117.11952012882,
        117.92836168682,
        116.95615162882,
        116.85851695582,
        117.21467206682
      ],
      "exit_codes": [
        0,
        0,
        0,
        0,
        0,
        0,
        0,
        0,
        0,
        0
      ]
    }
  ]
}
