{
  "results": [
    {
      "command": "cargo build --jobs 16 --release --example breakout",
      "mean": 74.91235622656001,
      "stddev": 0.3115538446118034,
      "median": 74.85660948706001,
      "user": 1100.1230770799998,
      "system": 28.598958,
      "min": 74.48076485956001,
      "max": 75.54690961956001,
      "times": [
        74.60231713356,
        74.85373674756,
        75.54690961956001,
        75.19257171956001,
        74.48076485956001,
        74.72547533856,
        74.88650547756001,
        74.81940642656001,
        74.85948222656,
        75.15639271656
      ],
      "exit_codes": [
        0,
        0,
        0,
        0,
        0,
        0,
        0,
        0,
        0,
        0
      ]
    }
  ]
}
