{"metrics":{"stress-test-fps.many_foxes.params.min":191523,"stress-test-fps.many_cubes.params-benchmark.std_dev":21633,"stress-test-fps.many_gizmos.params.mean":83510,"stress-test-fps.many_foxes.params.median":214436,"stress-test-fps.many_buttons.params.frames":2000,"wasm32-unknown-unknown.size":28552386,"stress-test-fps.many_lights.params.median":48525,"stress-test-fps.many_text2d.params.mean":59986,"stress-test-fps.many_materials.params.std_dev":1397,"stress-test-fps.many_text2d.params.median":60047,"stress-test-fps.bevymark.params-waves-60-per-wave-500-benchmark-mode-sprite.max":164254,"wasm32-unknown-unknown.optimized.size":17596470,"stress-test-fps.many_materials.params.mean":59605,"stress-test-fps.bevymark.params-waves-60-per-wave-500-benchmark-mode-mesh2d.median":54158,"stress-test-fps.many_gizmos.params.median":83536,"stress-test-fps.bevymark.params-waves-60-per-wave-500-benchmark-mode-mesh2d.duration":37600,"stress-test-fps.bevymark.params-waves-60-per-wave-500-benchmark-mode-sprite.frames":4000,"stress-test-fps.bevymark.params-waves-60-per-wave-500-benchmark-mode-sprite.std_dev":7028,"stress-test-fps.many_animated_sprites.params.frames":5000,"stress-test-fps.many_materials.params.max":63476,"stress-test-fps.many_buttons.params.std_dev":4655,"stress-test-fps.many_glyphs.params.frames":2000,"stress-test-fps.many_lights.params.max":61501,"stress-test-fps.many_sprites.params.std_dev":22967,"stress-test-fps.many_gizmos.params.duration":60481,"stress-test-fps.many_lights.params.duration":41423,"stress-test-fps.many_glyphs.params.max":107284,"stress-test-fps.many_animated_sprites.params.std_dev":46927,"stress-test-fps.many_lights.params.frames":2000,"stress-test-fps.many_gizmos.params.frames":5000,"stress-test-fps.many_materials.params.median":59607,"stress-test-fps.bevymark.params-waves-60-per-wave-500-benchmark-mode-sprite.duration":26459,"stress-test-fps.many_materials.params.duration":84274,"stress-test-fps.many_glyphs.params.mean":94781,"stress-test-fps.many_sprites.params.mean":560140,"stress-test-fps.many_animated_sprites.params.max":586112,"stress-test-fps.bevymark.params-waves-60-per-wave-500-benchmark-mode-sprite.mean":155940,"stress-test-fps.many_foxes.params.frames":5000,"stress-test-fps.many_gizmos.params.max":84585,"stress-test-fps.many_glyphs.params.duration":21198,"stress-test-fps.bevymark.params-waves-60-per-wave-500-benchmark-mode-sprite.median":158055,"stress-test-fps.many_sprites.params.median":549488,"stress-test-fps.bevymark.params-waves-60-per-wave-500-benchmark-mode-mesh2d.min":45489,"stress-test-fps.many_foxes.params.max":226668,"stress-test-fps.many_text2d.params.frames":6000,"stress-test-fps.many_lights.params.std_dev":3612,"stress-test-fps.many_materials.params.min":49663,"stress-test-fps.many_buttons.params.duration":49430,"stress-test-fps.many_foxes.params.mean":213293,"stress-test-fps.many_cubes.params-benchmark.max":293456,"stress-test-fps.bevymark.params-waves-60-per-wave-500-benchmark-mode-mesh2d.mean":54001,"stress-test-fps.many_lights.params.mean":49183,"stress-test-fps.many_sprites.params.duration":11692,"stress-test-fps.many_buttons.params.median":40341,"stress-test-fps.bevymark.params-waves-60-per-wave-500-benchmark-mode-sprite.min":135864,"stress-test-fps.many_gizmos.params.std_dev":586,"stress-test-fps.many_text2d.params.std_dev":710,"stress-test-fps.many_glyphs.params.median":95105,"stress-test-fps.many_sprites.params.frames":6000,"stress-test-fps.many_animated_sprites.params.duration":10036,"stress-test-fps.many_text2d.params.max":61302,"stress-test-fps.many_glyphs.params.min":48361,"stress-test-fps.many_text2d.params.min":57923,"stress-test-fps.many_foxes.params.std_dev":8656,"stress-test-fps.many_materials.params.frames":5000,"stress-test-fps.many_buttons.params.mean":41245,"stress-test-fps.many_text2d.params.duration":101327,"stress-test-fps.many_buttons.params.max":60831,"stress-test-fps.bevymark.params-waves-60-per-wave-500-benchmark-mode-mesh2d.max":67077,"stress-test-fps.many_animated_sprites.params.median":532893,"stress-test-fps.many_cubes.params-benchmark.frames":4000,"stress-test-fps.many_sprites.params.max":592447,"stress-test-fps.many_cubes.params-benchmark.min":213040,"stress-test-fps.many_cubes.params-benchmark.median":234276,"stress-test-fps.many_lights.params.min":44245,"stress-test-fps.many_buttons.params.min":36238,"stress-test-fps.many_animated_sprites.params.min":433319,"stress-test-fps.many_animated_sprites.params.mean":538035,"stress-test-fps.many_cubes.params-benchmark.mean":240983,"stress-test-fps.bevymark.params-waves-60-per-wave-500-benchmark-mode-mesh2d.std_dev":5987,"stress-test-fps.many_foxes.params.duration":24290,"stress-test-fps.many_sprites.params.min":527492,"stress-test-fps.many_glyphs.params.std_dev":12282,"stress-test-fps.many_cubes.params-benchmark.duration":17428,"stress-test-fps.many_gizmos.params.min":81955,"stress-test-fps.bevymark.params-waves-60-per-wave-500-benchmark-mode-mesh2d.frames":2000},"commit":"5dcfa52297f3ac20bf794edccb55e84b0c23f87d","timestamp":1755844226414,"commit_timestamp":1743824677000,"rust":{"stable":"rustc 1.88.0 (6b00bc388 2025-06-23)","nightly":"rustc 1.90.0-nightly (3014e79f9 2025-07-15)"},"host":{"hostname":"bevy-bench-01","os_version":"6.14.0-27-generic"}}