{
  "results": [
    {
      "command": "cargo build --jobs 8 --release --example breakout",
      "mean": 113.56308153446,
      "stddev": 0.30676834828511723,
      "median": 113.46388920036,
      "user": 854.86552106,
      "system": 22.74940376,
      "min": 113.29636220185999,
      "max": 114.30479256686,
      "times": [
        113.85313332786,
        113.47798979486,
        113.35938035486,
        113.32342783685999,
        113.29636220185999,
        113.44978860586,
        114.30479256686,
        113.59867602486,
        113.41782352786,
        113.54944110286
      ],
      "exit_codes": [
        0,
        0,
        0,
        0,
        0,
        0,
        0,
        0,
        0,
        0
      ]
    }
  ]
}
