{
  "results": [
    {
      "command": "cargo build --jobs 8 --release --example breakout",
      "mean": 117.15397186880003,
      "stddev": 0.10997295030981781,
      "median": 117.11771450009999,
      "user": 903.0984432199999,
      "system": 24.07918852,
      "min": 117.0737975816,
      "max": 117.4475437186,
      "times": [
        117.1432598836,
        117.2063278336,
        117.1454713646,
        117.1071671626,
        117.10263248860001,
        117.4475437186,
        117.0780896546,
        117.0737975816,
        117.1109236186,
        117.1245053816
      ],
      "exit_codes": [
        0,
        0,
        0,
        0,
        0,
        0,
        0,
        0,
        0,
        0
      ]
    }
  ]
}
