{
  "results": [
    {
      "command": "cargo build --jobs 16 --release --example breakout",
      "mean": 72.55022942913999,
      "stddev": 0.738414604205609,
      "median": 72.47757307234,
      "user": 1027.3286119,
      "system": 27.62682714,
      "min": 71.58205729184,
      "max": 73.88556507384,
      "times": [
        73.88556507384,
        72.44703284284,
        72.04047861284,
        71.58205729184,
        73.54361439284,
        72.66242072784,
        72.24002067584,
        72.50811330184,
        71.70905815284,
        72.88393321884
      ],
      "exit_codes": [
        0,
        0,
        0,
        0,
        0,
        0,
        0,
        0,
        0,
        0
      ]
    }
  ]
}
