{
  "results": [
    {
      "command": "cargo build --jobs 16 --release --example breakout",
      "mean": 98.13155417386,
      "stddev": 1.0414143526875592,
      "median": 98.15996711576,
      "user": 1373.52590644,
      "system": 33.75064788,
      "min": 96.46203087376,
      "max": 100.37209939776,
      "times": [
        97.77723176076,
        96.46203087376,
        98.52785621676,
        100.37209939776,
        97.82064604576,
        98.53214686776,
        97.88442641776,
        97.05469111476,
        98.44890522976,
        98.43550781376
      ],
      "exit_codes": [
        0,
        0,
        0,
        0,
        0,
        0,
        0,
        0,
        0,
        0
      ]
    }
  ]
}
