{
  "results": [
    {
      "command": "cargo build --jobs 16 --release --example breakout",
      "mean": 75.6568205226,
      "stddev": 0.23284807533360483,
      "median": 75.6802450587,
      "user": 1142.14622836,
      "system": 30.487072840000003,
      "min": 75.2268611557,
      "max": 75.9514244807,
      "times": [
        75.7960463097,
        75.4941429447,
        75.8453507647,
        75.2268611557,
        75.4967887717,
        75.9514244807,
        75.91020848870001,
        75.59327568970001,
        75.7672144277,
        75.4868921927
      ],
      "exit_codes": [
        0,
        0,
        0,
        0,
        0,
        0,
        0,
        0,
        0,
        0
      ]
    }
  ]
}
