{
  "results": [
    {
      "command": "cargo build --jobs 16 --release --example breakout",
      "mean": 81.7429608014,
      "stddev": 0.4642808903014523,
      "median": 81.79286187490001,
      "user": 1203.89255504,
      "system": 30.99709896,
      "min": 81.1114906649,
      "max": 82.6981199309,
      "times": [
        81.71301058990001,
        81.91976259890001,
        81.3312083169,
        81.2648160149,
        81.98118546590001,
        82.6981199309,
        81.5199518489,
        82.01734942290001,
        81.8727131599,
        81.1114906649
      ],
      "exit_codes": [
        0,
        0,
        0,
        0,
        0,
        0,
        0,
        0,
        0,
        0
      ]
    }
  ]
}
