{
  "results": [
    {
      "command": "cargo build --jobs 16 --release --example breakout",
      "mean": 74.07023461282002,
      "stddev": 0.4878465312752669,
      "median": 73.95992945632,
      "user": 1092.13364934,
      "system": 28.3456099,
      "min": 73.61422990232,
      "max": 74.93580615332,
      "times": [
        74.15232269232,
        73.90735590532,
        74.01735324832,
        73.62731175432,
        73.75682918732001,
        74.93580615332,
        73.74510252232001,
        73.61422990232,
        74.01250300732,
        74.93353175532
      ],
      "exit_codes": [
        0,
        0,
        0,
        0,
        0,
        0,
        0,
        0,
        0,
        0
      ]
    }
  ]
}
