{
  "results": [
    {
      "command": "cargo build --jobs 16 --release --example breakout",
      "mean": 70.72333952110002,
      "stddev": 0.5528538672844541,
      "median": 70.71536553640001,
      "user": 1002.9239279999999,
      "system": 27.40419362,
      "min": 69.32197657840001,
      "max": 71.3793952884,
      "times": [
        69.32197657840001,
        70.68522047340001,
        70.9311966954,
        71.3793952884,
        70.99058406340001,
        71.2003540484,
        70.6924448334,
        70.6552206334,
        70.6387163574,
        70.73828623940001
      ],
      "exit_codes": [
        0,
        0,
        0,
        0,
        0,
        0,
        0,
        0,
        0,
        0
      ]
    }
  ]
}
