{
  "results": [
    {
      "command": "cargo build --jobs 8 --release --example breakout",
      "mean": 120.40404525796002,
      "stddev": 0.11582433956810502,
      "median": 120.41581048016,
      "user": 903.6448725999999,
      "system": 23.797460179999998,
      "min": 120.26369374916,
      "max": 120.54078488216,
      "times": [
        120.54078488216,
        120.28545436316,
        120.37238817416001,
        120.54025682416,
        120.45923278616,
        120.48644485416,
        120.51453816416,
        120.29683672716,
        120.26369374916,
        120.28082205516
      ],
      "exit_codes": [
        0,
        0,
        0,
        0,
        0,
        0,
        0,
        0,
        0,
        0
      ]
    }
  ]
}
